Java9MokuaihuaKaifa/README.md
Java9MokuaihuaKaifa/__init__.py
Java9MokuaihuaKaifa/__main__.py
Java9MokuaihuaKaifa/file.epub
Java9MokuaihuaKaifa/index.html
Java9MokuaihuaKaifa/css/__init__.py
Java9MokuaihuaKaifa/css/annotations.css
Java9MokuaihuaKaifa/css/main.css
Java9MokuaihuaKaifa/css/normalize.css
Java9MokuaihuaKaifa/css/popup.css
Java9MokuaihuaKaifa/font/__init__.py
Java9MokuaihuaKaifa/font/fontello.eot
Java9MokuaihuaKaifa/font/fontello.svg
Java9MokuaihuaKaifa/font/fontello.ttf
Java9MokuaihuaKaifa/font/fontello.woff
Java9MokuaihuaKaifa/img/__init__.py
Java9MokuaihuaKaifa/img/annotator-glyph-sprite.png
Java9MokuaihuaKaifa/img/annotator-icon-sprite.png
Java9MokuaihuaKaifa/img/apple-touch-icon.png
Java9MokuaihuaKaifa/img/cancelfullscreen.png
Java9MokuaihuaKaifa/img/close.png
Java9MokuaihuaKaifa/img/fullscreen.png
Java9MokuaihuaKaifa/img/loader.gif
Java9MokuaihuaKaifa/img/menu-icon.png
Java9MokuaihuaKaifa/img/save.png
Java9MokuaihuaKaifa/img/saved.png
Java9MokuaihuaKaifa/img/settings-s.png
Java9MokuaihuaKaifa/img/settings.png
Java9MokuaihuaKaifa/img/star.png
Java9MokuaihuaKaifa/js/__init__.py
Java9MokuaihuaKaifa/js/epub.js
Java9MokuaihuaKaifa/js/epub.min.js
Java9MokuaihuaKaifa/js/epub.min.map
Java9MokuaihuaKaifa/js/hooks.min.js
Java9MokuaihuaKaifa/js/hooks.min.map
Java9MokuaihuaKaifa/js/reader.js
Java9MokuaihuaKaifa/js/reader.js.map
Java9MokuaihuaKaifa/js/reader.min.js
Java9MokuaihuaKaifa/js/reader.min.map
Java9MokuaihuaKaifa/js/hooks/__init__.py
Java9MokuaihuaKaifa/js/hooks/extensions/__init__.py
Java9MokuaihuaKaifa/js/hooks/extensions/highlight.js
Java9MokuaihuaKaifa/js/libs/__init__.py
Java9MokuaihuaKaifa/js/libs/jquery.min.js
Java9MokuaihuaKaifa/js/libs/localforage.min.js
Java9MokuaihuaKaifa/js/libs/screenfull.js
Java9MokuaihuaKaifa/js/libs/screenfull.min.js
Java9MokuaihuaKaifa/js/libs/zip.min.js
Java9MokuaihuaKaifa/js/plugins/__init__.py
Java9MokuaihuaKaifa/js/plugins/hypothesis.js
Java9MokuaihuaKaifa/js/plugins/search.js
java_9_mokuaihua_kaifa-2024.3.4.0.dist-info/METADATA
java_9_mokuaihua_kaifa-2024.3.4.0.dist-info/WHEEL
java_9_mokuaihua_kaifa-2024.3.4.0.dist-info/entry_points.txt
java_9_mokuaihua_kaifa-2024.3.4.0.dist-info/top_level.txt
java_9_mokuaihua_kaifa-2024.3.4.0.dist-info/RECORD
